neovim_gui/__init__.py
neovim_gui/cli.py
neovim_gui/gtk_ui.py
neovim_gui/qt_ui.py
neovim_gui/screen.py
neovim_gui/ui_bridge.py
nvimgtk-1.0.0.dist-info/LICENSE
nvimgtk-1.0.0.dist-info/METADATA
nvimgtk-1.0.0.dist-info/WHEEL
nvimgtk-1.0.0.dist-info/entry_points.txt
nvimgtk-1.0.0.dist-info/top_level.txt
nvimgtk-1.0.0.dist-info/RECORD
