Metadata-Version: 2.1
Name: nvimgtk
Version: 1.0.0
Summary: Gtk gui for neovim
License: Apache
License-File: LICENSE
Requires-Dist: pynvim >=0.1.3
Requires-Dist: click >=3.0
Requires-Dist: pygobject
